Pytolith/TagTypes.py
Pytolith/_TagSystem.py
Pytolith/__init__.py
Pytolith/halo2.layouts
Pytolith/Definitions/Fields.py
Pytolith/Definitions/Layout.py
Pytolith/Definitions/Package.py
Pytolith/Definitions/__init__.py
Pytolith/_TagLoader/Header.py
Pytolith/_TagLoader/Loader.py
Pytolith/_TagLoader/_FastTagLoaders.py
Pytolith-0.0.7.dist-info/METADATA
Pytolith-0.0.7.dist-info/WHEEL
Pytolith-0.0.7.dist-info/top_level.txt
Pytolith-0.0.7.dist-info/RECORD
