Metadata-Version: 2.1
Name: Pytolith
Version: 0.0.7
Summary: A simple package for reading Halo tag files.
Author-email: Num0005 <num0005@outlook.com>
Project-URL: Homepage, https://github.com/num0005/Pytolith
Project-URL: Issues, https://github.com/num0005/Pytolith/issues
Classifier: Programming Language :: Python :: 3
Classifier: License :: OSI Approved :: MIT License
Classifier: Operating System :: OS Independent
Requires-Python: >=3.10
